mediathek/__init__.py
mediathek/models.py
mediathek/channels/__init__.py
mediathek/channels/base.py
mediathek/channels/kika.py
mediathek-0.0.1.dist-info/LICENSE
mediathek-0.0.1.dist-info/METADATA
mediathek-0.0.1.dist-info/WHEEL
mediathek-0.0.1.dist-info/top_level.txt
mediathek-0.0.1.dist-info/RECORD
