Metadata-Version: 2.1
Name: mediathek
Version: 0.0.1
Summary: Crawler for German TV media centers
Home-page: https://github.com/Lanseuo/mediathek
Author: Lucas Hild
Author-email: contact@lucas-hild.de
License: MIT
Platform: UNKNOWN
Requires-Dist: requests
